<?xml version="1.0" encoding="utf-8" ?><dwsync><file name="instagram-blanc.png" server="ftp.2t3m.ca/dev.2t3mphotos.com/" local="3640712306" remote="3640712340" Dst="-1" /><file name="pinterest-blanc@2x.png" server="ftp.2t3m.ca/dev.2t3mphotos.com/" local="3640712306" remote="3640712340" Dst="-1" /><file name="facebook-blanc@2x.png" server="ftp.2t3m.ca/dev.2t3mphotos.com/" local="3640712306" remote="3640712340" Dst="-1" /><file name="pinterest-blanc.png" server="ftp.2t3m.ca/dev.2t3mphotos.com/" local="3640712306" remote="3640712460" Dst="-1" /><file name="instagram-blanc@2x.png" server="ftp.2t3m.ca/dev.2t3mphotos.com/" local="3640712306" remote="3640712340" Dst="-1" /><file name="facebook-blanc.png" server="ftp.2t3m.ca/dev.2t3mphotos.com/" local="3640712306" remote="3640782120" Dst="-1" /><file name="pinterest-blanc@3x.png" server="ftp.2t3m.ca/dev.2t3mphotos.com/" local="3640703212" remote="3640703280" Dst="-1" /><file name="logo-2t3mphotos@3x.png" server="ftp.2t3m.ca/dev.2t3mphotos.com/" local="3640703198" remote="3640703280" Dst="-1" /><file name="logo-2t3mphotos.png" server="ftp.2t3m.ca/dev.2t3mphotos.com/" local="3640703198" remote="3640703280" Dst="-1" /><file name="instagram-blanc@3x.png" server="ftp.2t3m.ca/dev.2t3mphotos.com/" local="3640703212" remote="3640703280" Dst="-1" /><file name="facebook-blanc@3x.png" server="ftp.2t3m.ca/dev.2t3mphotos.com/" local="3640703212" remote="3640703280" Dst="-1" /><file name="logo-2t3mphotos@2x.png" server="ftp.2t3m.ca/dev.2t3mphotos.com/" local="3640703198" remote="3640703280" Dst="-1" /><file name="bigPicture-background.png" server="ftp.2t3m.ca/dev.2t3mphotos.com/" local="3640707677" remote="3640707660" Dst="-1" /><file name="bigPicture-background@2x.png" server="ftp.2t3m.ca/dev.2t3mphotos.com/" local="3640707677" remote="3640707660" Dst="-1" /><file name="bouton-demande-information.png" server="ftp.2t3m.ca/dev.2t3mphotos.com/" local="3640712306" remote="3640712460" Dst="-1" /><file name="bouton-demande-information@2x.png" server="ftp.2t3m.ca/dev.2t3mphotos.com/" local="3640712306" remote="3640712340" Dst="-1" /><file name="cover-image-template.png" server="ftp.2t3m.ca/dev.2t3mphotos.com/" local="3640710318" remote="3640710360" Dst="-1" /><file name="cover-image-template@2x.png" server="ftp.2t3m.ca/dev.2t3mphotos.com/" local="3640710318" remote="3640710360" Dst="-1" /><file name="facebook-blanc-3.png" server="ftp.2t3m.ca/dev.2t3mphotos.com/" local="3640712306" remote="3640712340" Dst="-1" /><file name="pinterest-blanc-3@2x.png" server="ftp.2t3m.ca/dev.2t3mphotos.com/" local="3640712307" remote="3640712340" Dst="-1" /><file name="002-20141015-studio-reception-12x8.png" server="ftp.2t3m.ca/dev.2t3mphotos.com/" local="3640712306" remote="3640712340" Dst="-1" /><file name="plus-contour-14@2x.png" server="ftp.2t3m.ca/dev.2t3mphotos.com/" local="3640712308" remote="3640712340" Dst="-1" /><file name="asset-2@2x.png" server="ftp.2t3m.ca/dev.2t3mphotos.com/" local="3640712307" remote="3640712340" Dst="-1" /><file name="forfait-bronze.png" server="ftp.2t3m.ca/dev.2t3mphotos.com/" local="3640798083" remote="3640812360" Dst="-1" /><file name="plus-contour-9@2x.png" server="ftp.2t3m.ca/dev.2t3mphotos.com/" local="3640712307" remote="3640712340" Dst="-1" /><file name="IMG_0641-3-12x8.png" server="ftp.2t3m.ca/dev.2t3mphotos.com/" local="3640712306" remote="3640712340" Dst="-1" /><file name="forfait-or.png" server="ftp.2t3m.ca/dev.2t3mphotos.com/" local="3640798083" remote="3640812360" Dst="-1" /><file name="facebook-blanc-2.png" server="ftp.2t3m.ca/dev.2t3mphotos.com/" local="3640712306" remote="3640712340" Dst="-1" /><file name="facebook-blanc-5.png" server="ftp.2t3m.ca/dev.2t3mphotos.com/" local="3640712306" remote="3640712340" Dst="-1" /><file name="fond-bleu-v2.png" server="ftp.2t3m.ca/dev.2t3mphotos.com/" local="3640712306" remote="3640712340" Dst="-1" /><file name="facebook-blanc-4.png" server="ftp.2t3m.ca/dev.2t3mphotos.com/" local="3640712306" remote="3640712340" Dst="-1" /><file name="cover-portrait-corporatif.png" server="ftp.2t3m.ca/dev.2t3mphotos.com/" local="3640712306" remote="3640712340" Dst="-1" /><file name="20140223-chocolats-favoris-292-12x8-v2.png" server="ftp.2t3m.ca/dev.2t3mphotos.com/" local="3640712306" remote="3640712340" Dst="-1" /><file name="pinterest-blanc-1@2x.png" server="ftp.2t3m.ca/dev.2t3mphotos.com/" local="3640712306" remote="3640712340" Dst="-1" /><file name="cover-famille.png" server="ftp.2t3m.ca/dev.2t3mphotos.com/" local="3640712306" remote="3640712340" Dst="-1" /><file name="instagram-blanc-4.png" server="ftp.2t3m.ca/dev.2t3mphotos.com/" local="3640712306" remote="3640712340" Dst="-1" /><file name="asset-10.png" server="ftp.2t3m.ca/dev.2t3mphotos.com/" local="3640712306" remote="3640712340" Dst="-1" /><file name="plus-contour-1.png" server="ftp.2t3m.ca/dev.2t3mphotos.com/" local="3640712306" remote="3640712340" Dst="-1" /><file name="asset-11@2x.png" server="ftp.2t3m.ca/dev.2t3mphotos.com/" local="3640712308" remote="3640712340" Dst="-1" /><file name="asset-11.png" server="ftp.2t3m.ca/dev.2t3mphotos.com/" local="3640712306" remote="3640712340" Dst="-1" /><file name="instagram-blanc-5.png" server="ftp.2t3m.ca/dev.2t3mphotos.com/" local="3640712306" remote="3640712340" Dst="-1" /><file name="instagram-blanc-4@2x.png" server="ftp.2t3m.ca/dev.2t3mphotos.com/" local="3640712307" remote="3640712340" Dst="-1" /><file name="asset-5.png" server="ftp.2t3m.ca/dev.2t3mphotos.com/" local="3640712306" remote="3640712340" Dst="-1" /><file name="asset-4@2x.png" server="ftp.2t3m.ca/dev.2t3mphotos.com/" local="3640712307" remote="3640712340" Dst="-1" /><file name="asset-7.png" server="ftp.2t3m.ca/dev.2t3mphotos.com/" local="3640712306" remote="3640712340" Dst="-1" /><file name="pinterest-blanc-5@2x.png" server="ftp.2t3m.ca/dev.2t3mphotos.com/" local="3640712308" remote="3640712340" Dst="-1" /><file name="pinterest-blanc-4.png" server="ftp.2t3m.ca/dev.2t3mphotos.com/" local="3640712306" remote="3640712340" Dst="-1" /><file name="plus-contour-7@2x.png" server="ftp.2t3m.ca/dev.2t3mphotos.com/" local="3640712307" remote="3640712340" Dst="-1" /><file name="plus-contour-3.png" server="ftp.2t3m.ca/dev.2t3mphotos.com/" local="3640712306" remote="3640712340" Dst="-1" /><file name="asset-4.png" server="ftp.2t3m.ca/dev.2t3mphotos.com/" local="3640712306" remote="3640712340" Dst="-1" /><file name="asset-12.png" server="ftp.2t3m.ca/dev.2t3mphotos.com/" local="3640712306" remote="3640712340" Dst="-1" /><file name="asset-6.png" server="ftp.2t3m.ca/dev.2t3mphotos.com/" local="3640712306" remote="3640712340" Dst="-1" /><file name="plus-contour-12@2x.png" server="ftp.2t3m.ca/dev.2t3mphotos.com/" local="3640712308" remote="3640712340" Dst="-1" /><file name="asset-2.png" server="ftp.2t3m.ca/dev.2t3mphotos.com/" local="3640712306" remote="3640712340" Dst="-1" /><file name="plus-contour-1@2x.png" server="ftp.2t3m.ca/dev.2t3mphotos.com/" local="3640712307" remote="3640712340" Dst="-1" /><file name="plus-contour-7.png" server="ftp.2t3m.ca/dev.2t3mphotos.com/" local="3640712306" remote="3640712340" Dst="-1" /><file name="plus-contour-10@2x.png" server="ftp.2t3m.ca/dev.2t3mphotos.com/" local="3640712308" remote="3640712340" Dst="-1" /><file name="forfait-argent.png" server="ftp.2t3m.ca/dev.2t3mphotos.com/" local="3640798083" remote="3640812360" Dst="-1" /><file name="facebook-blanc-2@2x.png" server="ftp.2t3m.ca/dev.2t3mphotos.com/" local="3640712306" remote="3640712340" Dst="-1" /><file name="cover-photographe-culinaire@2x.png" server="ftp.2t3m.ca/dev.2t3mphotos.com/" local="3640712307" remote="3640712340" Dst="-1" /><file name="instagram-blanc-3.png" server="ftp.2t3m.ca/dev.2t3mphotos.com/" local="3640712306" remote="3640712340" Dst="-1" /><file name="asset-1.png" server="ftp.2t3m.ca/dev.2t3mphotos.com/" local="3640712306" remote="3640712340" Dst="-1" /><file name="plus-contour-2.png" server="ftp.2t3m.ca/dev.2t3mphotos.com/" local="3640712306" remote="3640712340" Dst="-1" /><file name="plus-contour-5.png" server="ftp.2t3m.ca/dev.2t3mphotos.com/" local="3640712306" remote="3640712340" Dst="-1" /><file name="pinterest-blanc-3.png" server="ftp.2t3m.ca/dev.2t3mphotos.com/" local="3640712306" remote="3640712340" Dst="-1" /><file name="logo-traitement-de-star.png" server="ftp.2t3m.ca/dev.2t3mphotos.com/" local="3640712306" remote="3640712340" Dst="-1" /><file name="Group 19@2x.png" server="ftp.2t3m.ca/dev.2t3mphotos.com/" local="3640712307" remote="3640712340" Dst="-1" /><file name="pinterest-blanc-5.png" server="ftp.2t3m.ca/dev.2t3mphotos.com/" local="3640712306" remote="3640712340" Dst="-1" /><file name="asset-8@2x.png" server="ftp.2t3m.ca/dev.2t3mphotos.com/" local="3640712307" remote="3640712340" Dst="-1" /><file name="facebook-blanc-5@2x.png" server="ftp.2t3m.ca/dev.2t3mphotos.com/" local="3640712308" remote="3640712340" Dst="-1" /><file name="pinterest-blanc-1.png" server="ftp.2t3m.ca/dev.2t3mphotos.com/" local="3640712306" remote="3640712340" Dst="-1" /><file name="pinterest-blanc-2@2x.png" server="ftp.2t3m.ca/dev.2t3mphotos.com/" local="3640712307" remote="3640712340" Dst="-1" /><file name="plus-contour-6.png" server="ftp.2t3m.ca/dev.2t3mphotos.com/" local="3640712306" remote="3640712340" Dst="-1" /><file name="plus-contour-4@2x.png" server="ftp.2t3m.ca/dev.2t3mphotos.com/" local="3640712307" remote="3640712340" Dst="-1" /><file name="logo-traitement-de-star@2x.png" server="ftp.2t3m.ca/dev.2t3mphotos.com/" local="3640712308" remote="3640712340" Dst="-1" /><file name="asset-6@2x.png" server="ftp.2t3m.ca/dev.2t3mphotos.com/" local="3640712307" remote="3640712340" Dst="-1" /><file name="Image 1@2x.png" server="ftp.2t3m.ca/dev.2t3mphotos.com/" local="3640712308" remote="3640712340" Dst="-1" /><file name="cover-photographe-immobilier.png" server="ftp.2t3m.ca/dev.2t3mphotos.com/" local="3640712306" remote="3640712340" Dst="-1" /><file name="plus-contour-3@2x.png" server="ftp.2t3m.ca/dev.2t3mphotos.com/" local="3640712307" remote="3640712340" Dst="-1" /><file name="asset-13@2x.png" server="ftp.2t3m.ca/dev.2t3mphotos.com/" local="3640712308" remote="3640712340" Dst="-1" /><file name="instagram-blanc-1.png" server="ftp.2t3m.ca/dev.2t3mphotos.com/" local="3640712306" remote="3640712340" Dst="-1" /><file name="Group 19.png" server="ftp.2t3m.ca/dev.2t3mphotos.com/" local="3640712306" remote="3640712340" Dst="-1" /><file name="forfait-argent@2x.png" server="ftp.2t3m.ca/dev.2t3mphotos.com/" local="3640798083" remote="3640812420" Dst="-1" /><file name="pinterest-blanc-2.png" server="ftp.2t3m.ca/dev.2t3mphotos.com/" local="3640712306" remote="3640712340" Dst="-1" /><file name="asset-8.png" server="ftp.2t3m.ca/dev.2t3mphotos.com/" local="3640712306" remote="3640712340" Dst="-1" /><file name="instagram-blanc-2.png" server="ftp.2t3m.ca/dev.2t3mphotos.com/" local="3640712306" remote="3640712340" Dst="-1" /><file name="plus-contour-8@2x.png" server="ftp.2t3m.ca/dev.2t3mphotos.com/" local="3640712307" remote="3640712340" Dst="-1" /><file name="plus-contour-11.png" server="ftp.2t3m.ca/dev.2t3mphotos.com/" local="3640712306" remote="3640712340" Dst="-1" /><file name="cover-famille@2x.png" server="ftp.2t3m.ca/dev.2t3mphotos.com/" local="3640712307" remote="3640712340" Dst="-1" /><file name="pinterest-blanc-4@2x.png" server="ftp.2t3m.ca/dev.2t3mphotos.com/" local="3640712307" remote="3640712340" Dst="-1" /><file name="asset-3.png" server="ftp.2t3m.ca/dev.2t3mphotos.com/" local="3640712306" remote="3640712340" Dst="-1" /><file name="plus-contour-6@2x.png" server="ftp.2t3m.ca/dev.2t3mphotos.com/" local="3640712307" remote="3640712340" Dst="-1" /><file name="montage-filles-sautent-hr.png" server="ftp.2t3m.ca/dev.2t3mphotos.com/" local="3640712306" remote="3640712340" Dst="-1" /><file name="002-20141015-studio-reception-12x8@2x.png" server="ftp.2t3m.ca/dev.2t3mphotos.com/" local="3640712307" remote="3640712340" Dst="-1" /><file name="plus-contour-12.png" server="ftp.2t3m.ca/dev.2t3mphotos.com/" local="3640712306" remote="3640712340" Dst="-1" /><file name="plus-contour-8.png" server="ftp.2t3m.ca/dev.2t3mphotos.com/" local="3640712306" remote="3640712340" Dst="-1" /><file name="asset-9@2x.png" server="ftp.2t3m.ca/dev.2t3mphotos.com/" local="3640712307" remote="3640712340" Dst="-1" /><file name="asset-3@2x.png" server="ftp.2t3m.ca/dev.2t3mphotos.com/" local="3640712307" remote="3640712340" Dst="-1" /><file name="cover-anniversaire-pour-filles.png" server="ftp.2t3m.ca/dev.2t3mphotos.com/" local="3640712306" remote="3640712340" Dst="-1" /><file name="asset-12@2x.png" server="ftp.2t3m.ca/dev.2t3mphotos.com/" local="3640712308" remote="3640712340" Dst="-1" /><file name="Image 1.png" server="ftp.2t3m.ca/dev.2t3mphotos.com/" local="3640712306" remote="3640712340" Dst="-1" /><file name="20120404_auto-neron_0037-12x8.png" server="ftp.2t3m.ca/dev.2t3mphotos.com/" local="3640712306" remote="3640712340" Dst="-1" /><file name="IMG_0804-ambiance-4x6@2x.png" server="ftp.2t3m.ca/dev.2t3mphotos.com/" local="3640712308" remote="3640712340" Dst="-1" /><file name="cover-anniversaire-pour-filles@2x.png" server="ftp.2t3m.ca/dev.2t3mphotos.com/" local="3640712307" remote="3640712340" Dst="-1" /><file name="20140223-chocolats-favoris-292-12x8-v2@2x.png" server="ftp.2t3m.ca/dev.2t3mphotos.com/" local="3640712307" remote="3640712340" Dst="-1" /><file name="plus-contour-5@2x.png" server="ftp.2t3m.ca/dev.2t3mphotos.com/" local="3640712307" remote="3640712460" Dst="-1" /><file name="facebook-blanc-4@2x.png" server="ftp.2t3m.ca/dev.2t3mphotos.com/" local="3640712307" remote="3640712460" Dst="-1" /><file name="facebook-blanc-1.png" server="ftp.2t3m.ca/dev.2t3mphotos.com/" local="3640712306" remote="3640712460" Dst="-1" /><file name="plus-contour2.png" server="ftp.2t3m.ca/dev.2t3mphotos.com/" local="3640712306" remote="3640712460" Dst="-1" /><file name="cover-portrait-corporatif@2x.png" server="ftp.2t3m.ca/dev.2t3mphotos.com/" local="3640712307" remote="3640712460" Dst="-1" /><file name="montage-filles-sautent-hr@2x.png" server="ftp.2t3m.ca/dev.2t3mphotos.com/" local="3640712308" remote="3640712460" Dst="-1" /><file name="cover-photographe-immobilier@2x.png" server="ftp.2t3m.ca/dev.2t3mphotos.com/" local="3640712308" remote="3640712460" Dst="-1" /><file name="instagram-blanc-2@2x.png" server="ftp.2t3m.ca/dev.2t3mphotos.com/" local="3640712307" remote="3640712460" Dst="-1" /><file name="plus-contour-4.png" server="ftp.2t3m.ca/dev.2t3mphotos.com/" local="3640712306" remote="3640712460" Dst="-1" /><file name="plus-contour-9.png" server="ftp.2t3m.ca/dev.2t3mphotos.com/" local="3640712306" remote="3640712460" Dst="-1" /><file name="IMG_0641-3-12x8@2x.png" server="ftp.2t3m.ca/dev.2t3mphotos.com/" local="3640712308" remote="3640712460" Dst="-1" /><file name="cover-photographe-culinaire.png" server="ftp.2t3m.ca/dev.2t3mphotos.com/" local="3640712306" remote="3640712460" Dst="-1" /><file name="asset-1@2x.png" server="ftp.2t3m.ca/dev.2t3mphotos.com/" local="3640712307" remote="3640712460" Dst="-1" /><file name="instagram-blanc-5@2x.png" server="ftp.2t3m.ca/dev.2t3mphotos.com/" local="3640712308" remote="3640712460" Dst="-1" /><file name="asset-9.png" server="ftp.2t3m.ca/dev.2t3mphotos.com/" local="3640712306" remote="3640712460" Dst="-1" /><file name="plus-contour-13@2x.png" server="ftp.2t3m.ca/dev.2t3mphotos.com/" local="3640712308" remote="3640712460" Dst="-1" /><file name="cover-prendre-rendez-vous@2x.png" server="ftp.2t3m.ca/dev.2t3mphotos.com/" local="3640712307" remote="3640712460" Dst="-1" /><file name="plus-contour-10.png" server="ftp.2t3m.ca/dev.2t3mphotos.com/" local="3640712306" remote="3640712460" Dst="-1" /><file name="plus-contour-2@2x.png" server="ftp.2t3m.ca/dev.2t3mphotos.com/" local="3640712307" remote="3640712460" Dst="-1" /><file name="cover-prendre-rendez-vous.png" server="ftp.2t3m.ca/dev.2t3mphotos.com/" local="3640712306" remote="3640712460" Dst="-1" /><file name="instagram-blanc-1@2x.png" server="ftp.2t3m.ca/dev.2t3mphotos.com/" local="3640712306" remote="3640712460" Dst="-1" /><file name="facebook-blanc-3@2x.png" server="ftp.2t3m.ca/dev.2t3mphotos.com/" local="3640712307" remote="3640712460" Dst="-1" /><file name="forfait-or@2x.png" server="ftp.2t3m.ca/dev.2t3mphotos.com/" local="3640798083" remote="3640812420" Dst="-1" /><file name="plus-contour-13.png" server="ftp.2t3m.ca/dev.2t3mphotos.com/" local="3640712306" remote="3640712460" Dst="-1" /><file name="asset-10@2x.png" server="ftp.2t3m.ca/dev.2t3mphotos.com/" local="3640712308" remote="3640712460" Dst="-1" /><file name="facebook-blanc-1@2x.png" server="ftp.2t3m.ca/dev.2t3mphotos.com/" local="3640712306" remote="3640712460" Dst="-1" /><file name="fond-bleu-v2@2x.png" server="ftp.2t3m.ca/dev.2t3mphotos.com/" local="3640712308" remote="3640712460" Dst="-1" /><file name="forfait-bronze@2x.png" server="ftp.2t3m.ca/dev.2t3mphotos.com/" local="3640798083" remote="3640812420" Dst="-1" /><file name="plus-contour2@2x.png" server="ftp.2t3m.ca/dev.2t3mphotos.com/" local="3640712307" remote="3640712520" Dst="-1" /><file name="20120404_auto-neron_0037-12x8@2x.png" server="ftp.2t3m.ca/dev.2t3mphotos.com/" local="3640712307" remote="3640712520" Dst="-1" /><file name="plus-contour-11@2x.png" server="ftp.2t3m.ca/dev.2t3mphotos.com/" local="3640712308" remote="3640712520" Dst="-1" /><file name="plus-contour-14.png" server="ftp.2t3m.ca/dev.2t3mphotos.com/" local="3640712306" remote="3640712520" Dst="-1" /><file name="asset-7@2x.png" server="ftp.2t3m.ca/dev.2t3mphotos.com/" local="3640712307" remote="3640712520" Dst="-1" /><file name="youtube-traitement-de-star@2x.png" server="ftp.2t3m.ca/dev.2t3mphotos.com/" local="3640795895" remote="3640797300" Dst="-1" /><file name="asset-13.png" server="ftp.2t3m.ca/dev.2t3mphotos.com/" local="3640712306" remote="3640797300" Dst="-1" /><file name="ambiance-traitement-de-star.png" server="ftp.2t3m.ca/dev.2t3mphotos.com/" local="3640795895" remote="3640797300" Dst="-1" /><file name="youtube-traitement-de-star.png" server="ftp.2t3m.ca/dev.2t3mphotos.com/" local="3640795895" remote="3640797300" Dst="-1" /><file name="IMG_0804-ambiance-4x6.png" server="ftp.2t3m.ca/dev.2t3mphotos.com/" local="3640712306" remote="3640797300" Dst="-1" /><file name="instagram-blanc-3@2x.png" server="ftp.2t3m.ca/dev.2t3mphotos.com/" local="3640712307" remote="3640797300" Dst="-1" /><file name="ambiance-traitement-de-star@2x.png" server="ftp.2t3m.ca/dev.2t3mphotos.com/" local="3640795895" remote="3640797300" Dst="-1" /><file name="arriere-plan-tarifs-traitement-de-star.png" server="ftp.2t3m.ca/dev.2t3mphotos.com/" local="3640806636" remote="3640806600" Dst="-1" /><file name="youtube-biographie-photographe.png" server="ftp.2t3m.ca/dev.2t3mphotos.com/" local="3640812127" remote="3640812360" Dst="-1" /><file name="asset-5@2x.png" server="ftp.2t3m.ca/dev.2t3mphotos.com/" local="3640712307" remote="3640812420" Dst="-1" /><file name="youtube-biographie-photographe@2x.png" server="ftp.2t3m.ca/dev.2t3mphotos.com/" local="3640812127" remote="3640812420" Dst="-1" /><file name="bouton-ecrire-un-courriel@2x.png" server="ftp.2t3m.ca/dev.2t3mphotos.com/" local="3640814332" remote="3640814340" Dst="-1" /><file name="bouton-ecrire-un-courriel.png" server="ftp.2t3m.ca/dev.2t3mphotos.com/" local="3640814332" remote="3640814340" Dst="-1" /><file name="pinterest-blanc-3@2x.png" server="ftp.2t3m.ca/public_html/2t3mphotos.ca/" local="3640712307" remote="3664377780" Dst="-1" /><file name="002-20141015-studio-reception-12x8.png" server="ftp.2t3m.ca/public_html/2t3mphotos.ca/" local="3640712306" remote="3664377780" Dst="-1" /><file name="facebook-blanc-2.png" server="ftp.2t3m.ca/public_html/2t3mphotos.ca/" local="3640712306" remote="3664377780" Dst="-1" /><file name="asset-2@2x.png" server="ftp.2t3m.ca/public_html/2t3mphotos.ca/" local="3640712307" remote="3664377780" Dst="-1" /><file name="plus-contour-5@2x.png" server="ftp.2t3m.ca/public_html/2t3mphotos.ca/" local="3640712307" remote="3664377780" Dst="-1" /><file name="forfait-or.png" server="ftp.2t3m.ca/public_html/2t3mphotos.ca/" local="3640798083" remote="3664377780" Dst="-1" /><file name="plus-contour2.png" server="ftp.2t3m.ca/public_html/2t3mphotos.ca/" local="3640712306" remote="3664377840" Dst="-1" /><file name="facebook-blanc-1.png" server="ftp.2t3m.ca/public_html/2t3mphotos.ca/" local="3640712306" remote="3640883760" Dst="-1" /><file name="pinterest-blanc@3x.png" server="ftp.2t3m.ca/public_html/2t3mphotos.ca/" local="3640703212" remote="3664377780" Dst="-1" /><file name="bouton-ecrire-un-courriel.png" server="ftp.2t3m.ca/public_html/2t3mphotos.ca/" local="3664377786" remote="3664377780" Dst="-1" /><file name="cover-portrait-corporatif@2x.png" server="ftp.2t3m.ca/public_html/2t3mphotos.ca/" local="3640712307" remote="3664377780" Dst="-1" /><file name="instagram-blanc-4@2x.png" server="ftp.2t3m.ca/public_html/2t3mphotos.ca/" local="3640712307" remote="3664377840" Dst="-1" /><file name="plus-contour-7@2x.png" server="ftp.2t3m.ca/public_html/2t3mphotos.ca/" local="3640712307" remote="3664377780" Dst="-1" /><file name="cover-portrait-corporatif.png" server="ftp.2t3m.ca/public_html/2t3mphotos.ca/" local="3640712306" remote="3664377780" Dst="-1" /><file name="asset-4.png" server="ftp.2t3m.ca/public_html/2t3mphotos.ca/" local="3640712306" remote="3664377780" Dst="-1" /><file name="asset-10.png" server="ftp.2t3m.ca/public_html/2t3mphotos.ca/" local="3640712306" remote="3664377780" Dst="-1" /><file name="asset-11@2x.png" server="ftp.2t3m.ca/public_html/2t3mphotos.ca/" local="3640712308" remote="3664377840" Dst="-1" /><file name="forfait-argent.png" server="ftp.2t3m.ca/public_html/2t3mphotos.ca/" local="3640798083" remote="3664377780" Dst="-1" /><file name="instagram-blanc-5.png" server="ftp.2t3m.ca/public_html/2t3mphotos.ca/" local="3640712306" remote="3664377780" Dst="-1" /><file name="facebook-blanc-2@2x.png" server="ftp.2t3m.ca/public_html/2t3mphotos.ca/" local="3640712306" remote="3664377780" Dst="-1" /><file name="asset-5.png" server="ftp.2t3m.ca/public_html/2t3mphotos.ca/" local="3640712306" remote="3664377780" Dst="-1" /><file name="asset-4@2x.png" server="ftp.2t3m.ca/public_html/2t3mphotos.ca/" local="3640712307" remote="3664377780" Dst="-1" /><file name="pinterest-blanc-5@2x.png" server="ftp.2t3m.ca/public_html/2t3mphotos.ca/" local="3640712308" remote="3664377780" Dst="-1" /><file name="pinterest-blanc-4.png" server="ftp.2t3m.ca/public_html/2t3mphotos.ca/" local="3640712306" remote="3640883760" Dst="-1" /><file name="asset-8@2x.png" server="ftp.2t3m.ca/public_html/2t3mphotos.ca/" local="3640712307" remote="3664377780" Dst="-1" /><file name="plus-contour-3.png" server="ftp.2t3m.ca/public_html/2t3mphotos.ca/" local="3640712306" remote="3664377840" Dst="-1" /><file name="cover-photographe-culinaire@2x.png" server="ftp.2t3m.ca/public_html/2t3mphotos.ca/" local="3640712307" remote="3664377780" Dst="-1" /><file name="asset-12.png" server="ftp.2t3m.ca/public_html/2t3mphotos.ca/" local="3640712306" remote="3664377840" Dst="-1" /><file name="plus-contour-12@2x.png" server="ftp.2t3m.ca/public_html/2t3mphotos.ca/" local="3640712308" remote="3640883760" Dst="-1" /><file name="instagram-blanc-2.png" server="ftp.2t3m.ca/public_html/2t3mphotos.ca/" local="3640712306" remote="3664377780" Dst="-1" /><file name="cover-photographe-immobilier@2x.png" server="ftp.2t3m.ca/public_html/2t3mphotos.ca/" local="3640712308" remote="3664377780" Dst="-1" /><file name="plus-contour-7.png" server="ftp.2t3m.ca/public_html/2t3mphotos.ca/" local="3640712306" remote="3664377840" Dst="-1" /><file name="plus-contour-6.png" server="ftp.2t3m.ca/public_html/2t3mphotos.ca/" local="3640712306" remote="3664377840" Dst="-1" /><file name="asset-3.png" server="ftp.2t3m.ca/public_html/2t3mphotos.ca/" local="3640712306" remote="3664377780" Dst="-1" /><file name="logo-2t3mphotos@2x.png" server="ftp.2t3m.ca/public_html/2t3mphotos.ca/" local="3640703198" remote="3664377840" Dst="-1" /><file name="instagram-blanc-2@2x.png" server="ftp.2t3m.ca/public_html/2t3mphotos.ca/" local="3640712307" remote="3664377840" Dst="-1" /><file name="asset-13@2x.png" server="ftp.2t3m.ca/public_html/2t3mphotos.ca/" local="3640712308" remote="3664377840" Dst="-1" /><file name="arriere-plan-tarifs-traitement-de-star.png" server="ftp.2t3m.ca/public_html/2t3mphotos.ca/" local="3640806636" remote="3664377780" Dst="-1" /><file name="plus-contour-4.png" server="ftp.2t3m.ca/public_html/2t3mphotos.ca/" local="3640712306" remote="3664377840" Dst="-1" /><file name="pinterest-blanc-3.png" server="ftp.2t3m.ca/public_html/2t3mphotos.ca/" local="3640712306" remote="3640883760" Dst="-1" /><file name="logo-2t3mphotos.png" server="ftp.2t3m.ca/public_html/2t3mphotos.ca/" local="3664376680" remote="3664376700" Dst="-1" /><file name="youtube-biographie-photographe.png" server="ftp.2t3m.ca/public_html/2t3mphotos.ca/" local="3640812127" remote="3664377780" Dst="-1" /><file name="facebook-blanc@2x.png" server="ftp.2t3m.ca/public_html/2t3mphotos.ca/" local="3640712306" remote="3664377840" Dst="-1" /><file name="002-20141015-studio-reception-12x8@2x.png" server="ftp.2t3m.ca/public_html/2t3mphotos.ca/" local="3640712307" remote="3664377840" Dst="-1" /><file name="20140223-chocolats-favoris-292-12x8-v2@2x.png" server="ftp.2t3m.ca/public_html/2t3mphotos.ca/" local="3640712307" remote="3664377840" Dst="-1" /><file name="plus-contour-8@2x.png" server="ftp.2t3m.ca/public_html/2t3mphotos.ca/" local="3640712307" remote="3664377840" Dst="-1" /><file name="logo-traitement-de-star@2x.png" server="ftp.2t3m.ca/public_html/2t3mphotos.ca/" local="3640712308" remote="3640883820" Dst="-1" /><file name="cover-anniversaire-pour-filles.png" server="ftp.2t3m.ca/public_html/2t3mphotos.ca/" local="3640712306" remote="3664377840" Dst="-1" /><file name="cover-photographe-immobilier.png" server="ftp.2t3m.ca/public_html/2t3mphotos.ca/" local="3640712306" remote="3640883820" Dst="-1" /><file name="cover-photographe-culinaire.png" server="ftp.2t3m.ca/public_html/2t3mphotos.ca/" local="3640712306" remote="3664377840" Dst="-1" /><file name="forfait-argent@2x.png" server="ftp.2t3m.ca/public_html/2t3mphotos.ca/" local="3640798083" remote="3664377780" Dst="-1" /><file name="cover-famille@2x.png" server="ftp.2t3m.ca/public_html/2t3mphotos.ca/" local="3640712307" remote="3664377780" Dst="-1" /><file name="facebook-blanc@3x.png" server="ftp.2t3m.ca/public_html/2t3mphotos.ca/" local="3640703212" remote="3664377840" Dst="-1" /><file name="instagram-blanc-5@2x.png" server="ftp.2t3m.ca/public_html/2t3mphotos.ca/" local="3640712308" remote="3664377840" Dst="-1" /><file name="instagram-blanc@2x.png" server="ftp.2t3m.ca/public_html/2t3mphotos.ca/" local="3640712306" remote="3664377780" Dst="-1" /><file name="plus-contour-11.png" server="ftp.2t3m.ca/public_html/2t3mphotos.ca/" local="3640712306" remote="3664377780" Dst="-1" /><file name="bouton-demande-information.png" server="ftp.2t3m.ca/public_html/2t3mphotos.ca/" local="3664377775" remote="3664377840" Dst="-1" /><file name="pinterest-blanc-4@2x.png" server="ftp.2t3m.ca/public_html/2t3mphotos.ca/" local="3640712307" remote="3664377840" Dst="-1" /><file name="plus-contour-10.png" server="ftp.2t3m.ca/public_html/2t3mphotos.ca/" local="3640712306" remote="3664377780" Dst="-1" /><file name="plus-contour-2@2x.png" server="ftp.2t3m.ca/public_html/2t3mphotos.ca/" local="3640712307" remote="3664377840" Dst="-1" /><file name="plus-contour-12.png" server="ftp.2t3m.ca/public_html/2t3mphotos.ca/" local="3640712306" remote="3664377780" Dst="-1" /><file name="forfait-or@2x.png" server="ftp.2t3m.ca/public_html/2t3mphotos.ca/" local="3640798083" remote="3664377780" Dst="-1" /><file name="pinterest-blanc.png" server="ftp.2t3m.ca/public_html/2t3mphotos.ca/" local="3640712306" remote="3664377840" Dst="-1" /><file name="plus-contour-13.png" server="ftp.2t3m.ca/public_html/2t3mphotos.ca/" local="3640712306" remote="3664377840" Dst="-1" /><file name="facebook-blanc.png" server="ftp.2t3m.ca/public_html/2t3mphotos.ca/" local="3640712306" remote="3664378620" Dst="-1" /><file name="Image 1.png" server="ftp.2t3m.ca/public_html/2t3mphotos.ca/" local="3640712306" remote="3664377840" Dst="-1" /><file name="forfait-bronze@2x.png" server="ftp.2t3m.ca/public_html/2t3mphotos.ca/" local="3640798083" remote="3640883820" Dst="-1" /><file name="asset-12@2x.png" server="ftp.2t3m.ca/public_html/2t3mphotos.ca/" local="3640712308" remote="3640883820" Dst="-1" /><file name="IMG_0804-ambiance-4x6@2x.png" server="ftp.2t3m.ca/public_html/2t3mphotos.ca/" local="3640712308" remote="3664377840" Dst="-1" /><file name="plus-contour-11@2x.png" server="ftp.2t3m.ca/public_html/2t3mphotos.ca/" local="3640712308" remote="3640883820" Dst="-1" /><file name="plus-contour-14.png" server="ftp.2t3m.ca/public_html/2t3mphotos.ca/" local="3640712306" remote="3664377840" Dst="-1" /><file name="ambiance-traitement-de-star@2x.png" server="ftp.2t3m.ca/public_html/2t3mphotos.ca/" local="3640795895" remote="3664377840" Dst="-1" /><file name="asset-7@2x.png" server="ftp.2t3m.ca/public_html/2t3mphotos.ca/" local="3640712307" remote="3664377840" Dst="-1" /><file name="facebook-blanc-3.png" server="ftp.2t3m.ca/public_html/2t3mphotos.ca/" local="3640712306" remote="3664377780" Dst="-1" /><file name="IMG_0641-3-12x8.png" server="ftp.2t3m.ca/public_html/2t3mphotos.ca/" local="3640712306" remote="3664377780" Dst="-1" /><file name="facebook-blanc-4@2x.png" server="ftp.2t3m.ca/public_html/2t3mphotos.ca/" local="3640712307" remote="3664377840" Dst="-1" /><file name="montage-filles-sautent-hr@2x.png" server="ftp.2t3m.ca/public_html/2t3mphotos.ca/" local="3640712308" remote="3664377780" Dst="-1" /><file name="pinterest-blanc@2x.png" server="ftp.2t3m.ca/public_html/2t3mphotos.ca/" local="3640712306" remote="3664377780" Dst="-1" /><file name="facebook-blanc-5.png" server="ftp.2t3m.ca/public_html/2t3mphotos.ca/" local="3640712306" remote="3664377780" Dst="-1" /><file name="fond-bleu-v2.png" server="ftp.2t3m.ca/public_html/2t3mphotos.ca/" local="3640712306" remote="3664377780" Dst="-1" /><file name="youtube-traitement-de-star@2x.png" server="ftp.2t3m.ca/public_html/2t3mphotos.ca/" local="3640795895" remote="3664377780" Dst="-1" /><file name="cover-famille.png" server="ftp.2t3m.ca/public_html/2t3mphotos.ca/" local="3640712306" remote="3664377840" Dst="-1" /><file name="instagram-blanc-4.png" server="ftp.2t3m.ca/public_html/2t3mphotos.ca/" local="3640712306" remote="3664377780" Dst="-1" /><file name="ambiance-traitement-de-star.png" server="ftp.2t3m.ca/public_html/2t3mphotos.ca/" local="3640795895" remote="3664377780" Dst="-1" /><file name="logo-2t3mphotos@3x.png" server="ftp.2t3m.ca/public_html/2t3mphotos.ca/" local="3640703198" remote="3664377780" Dst="-1" /><file name="asset-7.png" server="ftp.2t3m.ca/public_html/2t3mphotos.ca/" local="3640712306" remote="3664377840" Dst="-1" /><file name="asset-13.png" server="ftp.2t3m.ca/public_html/2t3mphotos.ca/" local="3640712306" remote="3664377780" Dst="-1" /><file name="pinterest-blanc-5.png" server="ftp.2t3m.ca/public_html/2t3mphotos.ca/" local="3640712306" remote="3664377780" Dst="-1" /><file name="asset-6.png" server="ftp.2t3m.ca/public_html/2t3mphotos.ca/" local="3640712306" remote="3664377840" Dst="-1" /><file name="asset-2.png" server="ftp.2t3m.ca/public_html/2t3mphotos.ca/" local="3640712306" remote="3664377780" Dst="-1" /><file name="pinterest-blanc-1.png" server="ftp.2t3m.ca/public_html/2t3mphotos.ca/" local="3640712306" remote="3664377780" Dst="-1" /><file name="plus-contour-10@2x.png" server="ftp.2t3m.ca/public_html/2t3mphotos.ca/" local="3640712308" remote="3664377780" Dst="-1" /><file name="instagram-blanc-3.png" server="ftp.2t3m.ca/public_html/2t3mphotos.ca/" local="3640712306" remote="3664377780" Dst="-1" /><file name="instagram-blanc-1.png" server="ftp.2t3m.ca/public_html/2t3mphotos.ca/" local="3640712306" remote="3664377840" Dst="-1" /><file name="pinterest-blanc-2.png" server="ftp.2t3m.ca/public_html/2t3mphotos.ca/" local="3640712306" remote="3664377780" Dst="-1" /><file name="plus-contour-5.png" server="ftp.2t3m.ca/public_html/2t3mphotos.ca/" local="3640712306" remote="3664377780" Dst="-1" /><file name="logo-traitement-de-star.png" server="ftp.2t3m.ca/public_html/2t3mphotos.ca/" local="3640712306" remote="3664377780" Dst="-1" /><file name="Group 19@2x.png" server="ftp.2t3m.ca/public_html/2t3mphotos.ca/" local="3640712307" remote="3664377780" Dst="-1" /><file name="plus-contour-9.png" server="ftp.2t3m.ca/public_html/2t3mphotos.ca/" local="3640712306" remote="3664377780" Dst="-1" /><file name="facebook-blanc-5@2x.png" server="ftp.2t3m.ca/public_html/2t3mphotos.ca/" local="3640712308" remote="3664377780" Dst="-1" /><file name="Image 1@2x.png" server="ftp.2t3m.ca/public_html/2t3mphotos.ca/" local="3640712308" remote="3664377780" Dst="-1" /><file name="IMG_0641-3-12x8@2x.png" server="ftp.2t3m.ca/public_html/2t3mphotos.ca/" local="3640712308" remote="3664377780" Dst="-1" /><file name="asset-8.png" server="ftp.2t3m.ca/public_html/2t3mphotos.ca/" local="3640712306" remote="3664377840" Dst="-1" /><file name="asset-1@2x.png" server="ftp.2t3m.ca/public_html/2t3mphotos.ca/" local="3640712307" remote="3664377840" Dst="-1" /><file name="asset-9.png" server="ftp.2t3m.ca/public_html/2t3mphotos.ca/" local="3640712306" remote="3640883820" Dst="-1" /><file name="asset-5@2x.png" server="ftp.2t3m.ca/public_html/2t3mphotos.ca/" local="3640712307" remote="3664377840" Dst="-1" /><file name="youtube-biographie-photographe@2x.png" server="ftp.2t3m.ca/public_html/2t3mphotos.ca/" local="3640812127" remote="3664377840" Dst="-1" /><file name="facebook-blanc-3@2x.png" server="ftp.2t3m.ca/public_html/2t3mphotos.ca/" local="3640712307" remote="3664377780" Dst="-1" /><file name="cover-prendre-rendez-vous.png" server="ftp.2t3m.ca/public_html/2t3mphotos.ca/" local="3640712306" remote="3664377780" Dst="-1" /><file name="instagram-blanc-1@2x.png" server="ftp.2t3m.ca/public_html/2t3mphotos.ca/" local="3640712306" remote="3640883820" Dst="-1" /><file name="IMG_0804-ambiance-4x6.png" server="ftp.2t3m.ca/public_html/2t3mphotos.ca/" local="3640712306" remote="3664377840" Dst="-1" /><file name="asset-10@2x.png" server="ftp.2t3m.ca/public_html/2t3mphotos.ca/" local="3640712308" remote="3664377840" Dst="-1" /><file name="instagram-blanc-3@2x.png" server="ftp.2t3m.ca/public_html/2t3mphotos.ca/" local="3640712307" remote="3640883820" Dst="-1" /><file name="fond-bleu-v2@2x.png" server="ftp.2t3m.ca/public_html/2t3mphotos.ca/" local="3640712308" remote="3664377840" Dst="-1" /><file name="20120404_auto-neron_0037-12x8@2x.png" server="ftp.2t3m.ca/public_html/2t3mphotos.ca/" local="3640712307" remote="3664377840" Dst="-1" /><file name="cover-image-template@2x.png" server="ftp.2t3m.ca/public_html/2t3mphotos.ca/" local="3640710318" remote="3664377840" Dst="-1" /><file name="facebook-blanc-4.png" server="ftp.2t3m.ca/public_html/2t3mphotos.ca/" local="3640712306" remote="3664377780" Dst="-1" /><file name="asset-11.png" server="ftp.2t3m.ca/public_html/2t3mphotos.ca/" local="3640712306" remote="3664377840" Dst="-1" /><file name="plus-contour-3@2x.png" server="ftp.2t3m.ca/public_html/2t3mphotos.ca/" local="3640712307" remote="3664377840" Dst="-1" /><file name="plus-contour-8.png" server="ftp.2t3m.ca/public_html/2t3mphotos.ca/" local="3640712306" remote="3664377840" Dst="-1" /><file name="plus-contour2@2x.png" server="ftp.2t3m.ca/public_html/2t3mphotos.ca/" local="3640712307" remote="3664377840" Dst="-1" /><file name="cover-anniversaire-pour-filles@2x.png" server="ftp.2t3m.ca/public_html/2t3mphotos.ca/" local="3640712307" remote="3664377840" Dst="-1" /><file name="bouton-ecrire-un-courriel@2x.png" server="ftp.2t3m.ca/public_html/2t3mphotos.ca/" local="3664377786" remote="3664377780" Dst="-1" /><file name="plus-contour-9@2x.png" server="ftp.2t3m.ca/public_html/2t3mphotos.ca/" local="3640712307" remote="3664377780" Dst="-1" /><file name="forfait-bronze.png" server="ftp.2t3m.ca/public_html/2t3mphotos.ca/" local="3640798083" remote="3664377780" Dst="-1" /><file name="plus-contour-14@2x.png" server="ftp.2t3m.ca/public_html/2t3mphotos.ca/" local="3640712308" remote="3664377780" Dst="-1" /><file name="pinterest-blanc-1@2x.png" server="ftp.2t3m.ca/public_html/2t3mphotos.ca/" local="3640712306" remote="3664377840" Dst="-1" /><file name="plus-contour-1.png" server="ftp.2t3m.ca/public_html/2t3mphotos.ca/" local="3640712306" remote="3664377780" Dst="-1" /><file name="plus-contour-2.png" server="ftp.2t3m.ca/public_html/2t3mphotos.ca/" local="3640712306" remote="3664377840" Dst="-1" /><file name="instagram-blanc.png" server="ftp.2t3m.ca/public_html/2t3mphotos.ca/" local="3640712306" remote="3664377780" Dst="-1" /><file name="20140223-chocolats-favoris-292-12x8-v2.png" server="ftp.2t3m.ca/public_html/2t3mphotos.ca/" local="3640712306" remote="3664377780" Dst="-1" /><file name="plus-contour-1@2x.png" server="ftp.2t3m.ca/public_html/2t3mphotos.ca/" local="3640712307" remote="3640883880" Dst="-1" /><file name="asset-6@2x.png" server="ftp.2t3m.ca/public_html/2t3mphotos.ca/" local="3640712307" remote="3664377780" Dst="-1" /><file name="asset-1.png" server="ftp.2t3m.ca/public_html/2t3mphotos.ca/" local="3640712306" remote="3664377780" Dst="-1" /><file name="youtube-traitement-de-star.png" server="ftp.2t3m.ca/public_html/2t3mphotos.ca/" local="3640795895" remote="3664377840" Dst="-1" /><file name="plus-contour-4@2x.png" server="ftp.2t3m.ca/public_html/2t3mphotos.ca/" local="3640712307" remote="3664377780" Dst="-1" /><file name="pinterest-blanc-2@2x.png" server="ftp.2t3m.ca/public_html/2t3mphotos.ca/" local="3640712307" remote="3664377780" Dst="-1" /><file name="bigPicture-background.png" server="ftp.2t3m.ca/public_html/2t3mphotos.ca/" local="3640707677" remote="3664377840" Dst="-1" /><file name="asset-3@2x.png" server="ftp.2t3m.ca/public_html/2t3mphotos.ca/" local="3640712307" remote="3640883880" Dst="-1" /><file name="plus-contour-6@2x.png" server="ftp.2t3m.ca/public_html/2t3mphotos.ca/" local="3640712307" remote="3664377780" Dst="-1" /><file name="Group 19.png" server="ftp.2t3m.ca/public_html/2t3mphotos.ca/" local="3640712306" remote="3664377780" Dst="-1" /><file name="plus-contour-13@2x.png" server="ftp.2t3m.ca/public_html/2t3mphotos.ca/" local="3640712308" remote="3664377840" Dst="-1" /><file name="bouton-demande-information@2x.png" server="ftp.2t3m.ca/public_html/2t3mphotos.ca/" local="3664377775" remote="3664377780" Dst="-1" /><file name="asset-9@2x.png" server="ftp.2t3m.ca/public_html/2t3mphotos.ca/" local="3640712307" remote="3664377780" Dst="-1" /><file name="facebook-blanc-1@2x.png" server="ftp.2t3m.ca/public_html/2t3mphotos.ca/" local="3640712306" remote="3664377840" Dst="-1" /><file name="20120404_auto-neron_0037-12x8.png" server="ftp.2t3m.ca/public_html/2t3mphotos.ca/" local="3640712306" remote="3664377840" Dst="-1" /><file name="cover-image-template.png" server="ftp.2t3m.ca/public_html/2t3mphotos.ca/" local="3640710318" remote="3664377840" Dst="-1" /><file name="bigPicture-background@2x.png" server="ftp.2t3m.ca/public_html/2t3mphotos.ca/" local="3640707677" remote="3664377840" Dst="-1" /><file name="instagram-blanc@3x.png" server="ftp.2t3m.ca/public_html/2t3mphotos.ca/" local="3640703212" remote="3664377840" Dst="-1" /><file name="cover-prendre-rendez-vous@2x.png" server="ftp.2t3m.ca/public_html/2t3mphotos.ca/" local="3640712307" remote="3664377780" Dst="-1" /><file name="montage-filles-sautent-hr.png" server="ftp.2t3m.ca/public_html/2t3mphotos.ca/" local="3640712306" remote="3664377840" Dst="-1" /><file name="cover-photographe-culinaire@2x.jpg" server="ftp.2t3m.ca/public_html/2t3mphotos.ca/" local="3640959657" remote="3664377780" Dst="-1" /><file name="cover-photographe-immobilier@2x.jpg" server="ftp.2t3m.ca/public_html/2t3mphotos.ca/" local="3640959662" remote="3664377840" Dst="-1" /><file name="cover-portrait-corporatif@2x.jpg" server="ftp.2t3m.ca/public_html/2t3mphotos.ca/" local="3640959666" remote="3664377780" Dst="-1" /><file name="cover-famille@2x.jpg" server="ftp.2t3m.ca/public_html/2t3mphotos.ca/" local="3640959675" remote="3664377840" Dst="-1" /><file name="cover-prendre-rendez-vous@2x.jpg" server="ftp.2t3m.ca/public_html/2t3mphotos.ca/" local="3640959669" remote="3664377780" Dst="-1" /><file name="cover-anniversaire-pour-filles@2x.jpg" server="ftp.2t3m.ca/public_html/2t3mphotos.ca/" local="3640959672" remote="3664377840" Dst="-1" /><file name="cover-image-template@2x.jpg" server="ftp.2t3m.ca/public_html/2t3mphotos.ca/" local="3640959680" remote="3664377840" Dst="-1" /><file name="cover-photographe-hotel.png" server="ftp.2t3m.ca/public_html/2t3mphotos.ca/" local="3664378371" remote="3664378380" Dst="-1" /><file name="cover-photographe-hotel@2x.png" server="ftp.2t3m.ca/public_html/2t3mphotos.ca/" local="3664378371" remote="3664378380" Dst="-1" /><file name="cover-photographe-hotel@2x.jpg" server="ftp.2t3m.ca/public_html/2t3mphotos.ca/" local="3664378543" remote="3664378500" Dst="-1" /></dwsync>